fancy_dick/__init__.py
fancy_dick/dick.py
fancy_dick-0.1.1.dist-info/WHEEL
fancy_dick-0.1.1.dist-info/METADATA
fancy_dick-0.1.1.dist-info/RECORD
